{
  "id": 28,
  "species_id": 24,
  "form_id": 3,
  "name": "Deerling",
  "species": "Season Pokémon",
  "asset_folder": "024c_deerling_autumn",
  "types": [
    "Normal",
    "Grass"
  ],
  "base_stats": {
    "hp": 60,
    "attack": 60,
    "defense": 50,
    "sp_attack": 40,
    "sp_defense": 50,
    "speed": 75,
    "range": 3
  },
  "ability_ids": [
    34,
    157
  ],
  "cost": 200,
  "evolution_cost": 600,
  "evolves_into": [
    25
  ],
  "is_legendary": false,
  "archetype": "scout",
  "description": "Deerling have different scents depending on the season. In this form, Deerling have a softly sweet scent that lingers in the nose.",
  "measurements": {
    "height": 0.6,
    "weight": 19.5
  },
  "portrait_credits": [
    "Emmuffin"
  ],
  "sprite_credits": [
    "baronessfaron"
  ],
  "hidden_ability": 32,
  "level_up_moves": [
    {
      "level": 1,
      "move_id": 33
    },
    {
      "level": 4,
      "move_id": 45
    },
    {
      "level": 7,
      "move_id": 28
    },
    {
      "level": 10,
      "move_id": 24
    },
    {
      "level": 13,
      "move_id": 73
    },
    {
      "level": 16,
      "move_id": 331
    },
    {
      "level": 20,
      "move_id": 36
    },
    {
      "level": 24,
      "move_id": 428
    },
    {
      "level": 28,
      "move_id": 412
    },
    {
      "level": 32,
      "move_id": 204
    },
    {
      "level": 37,
      "move_id": 38
    },
    {
      "level": 42,
      "move_id": 76
    }
  ],
  "tm_moves": [
    34,
    36,
    38,
    76,
    86,
    91,
    97,
    113,
    156,
    164,
    182,
    202,
    203,
    204,
    214,
    226,
    240,
    241,
    247,
    263,
    270,
    283,
    313,
    331,
    345,
    402,
    412,
    428,
    437,
    447,
    523,
    528,
    580,
    583,
    803,
    851,
    885
  ],
  "egg_moves": [
    29,
    97,
    214,
    226,
    235,
    313,
    388
  ],
  "equipped_moves": [
    36,
    331
  ]
}
